greetings.py
fnexchange_sample_plugin-1.0.1.dist-info/DESCRIPTION.rst
fnexchange_sample_plugin-1.0.1.dist-info/METADATA
fnexchange_sample_plugin-1.0.1.dist-info/RECORD
fnexchange_sample_plugin-1.0.1.dist-info/WHEEL
fnexchange_sample_plugin-1.0.1.dist-info/metadata.json
fnexchange_sample_plugin-1.0.1.dist-info/top_level.txt
