Metadata-Version: 2.0
Name: fnexchange-sample-plugin
Version: 1.0.1
Summary: A sample fnExchange plugin
Home-page: UNKNOWN
Author: Bhumil Haria
Author-email: bhumilharia@gmail.com
License: Apache
Keywords: fnexchange plugin
Platform: any
Classifier: Development Status :: 4 - Beta
Classifier: Intended Audience :: Developers
Classifier: License :: OSI Approved :: Apache Software License
Classifier: Operating System :: POSIX
Classifier: Operating System :: MacOS
Classifier: Operating System :: Unix
Classifier: Operating System :: Microsoft :: Windows
Classifier: Programming Language :: Python
Classifier: Programming Language :: Python :: 2
Classifier: Programming Language :: Python :: 3
Requires-Dist: fnexchange
Requires-Dist: six (==1.10.0)
Requires-Dist: tornado (==4.4.2)
